bible9000/NagysNotes.sbbk
bible9000/__init__.py
bible9000/__main__.py
bible9000/admin_ops.py
bible9000/biblia.sqlt3
bible9000/fast_path.py
bible9000/main.py
bible9000/pannel.py
bible9000/report_html.py
bible9000/sierra_dao.py
bible9000/sierra_fav.py
bible9000/sierra_note.py
bible9000/tests.py
bible9000/tui.py
bible9000/words.py
bible9000-2025.10.3.data/data/NagysNotes.sbbk
bible9000-2025.10.3.data/data/biblia.sqlt3
bible9000-2025.10.3.dist-info/METADATA
bible9000-2025.10.3.dist-info/WHEEL
bible9000-2025.10.3.dist-info/top_level.txt
bible9000-2025.10.3.dist-info/RECORD
