Metadata-Version: 2.4
Name: Bible9000
Version: 2025.10.3
Summary: Ancient Wisdom Designed for Our Day!
Home-page: http://MightyMaxims.com
Download-URL: https://github.com/DoctorQuote/The-Stick-of-Joseph
Author: Randall Nagy
Author-email: Randall Nagy <r.a.nagy@gmail.com>
Maintainer-email: Randall Nagy <r.a.nagy@gmail.com>
License-Expression: MIT
Project-URL: Homepage, https://github.com/DoctorQuote/The-Stick-of-Joseph
Project-URL: Bug Tracker, https://github.com/DoctorQuote/The-Stick-of-Joseph/issues
Platform: Cross-Platform CLI / TUI
Classifier: Programming Language :: Python :: 3
Requires-Python: >=3.6
Dynamic: author
Dynamic: download-url
Dynamic: home-page
Dynamic: platform
